Workbook

Sheet Start Here
A2: Freelancer Quarterly Tax & Expense Tracker — 2026 Edition
A4: How to use this workbook:
A5: 1. Log every client payment on the 'Income Log' tab as it arrives.
A6: 2. Log every business expense on the 'Expense Log' tab — pick a category from the dropdown; it maps to real IRS Schedule C lines (see the PDF guide).
A7: 3. Meals default to 50% deductible — the sheet applies that automatically; every other category defaults to 100% but you can override the % on any row.
A8: 4. Open the 'Quarterly Tax Estimator' tab and type your projected full-year net profit — it calculates your exact self-employment tax using the real 2026 formula.
A9: 5. Check the 'Dashboard' tab any time for a live snapshot: income, expenses, net profit, and how many days until your next quarterly payment is due.
A11: This workbook is a bookkeeping and estimating tool, not tax software — it does not file anything or replace a preparer. It exists so your numbers are already organized when tax time comes.

Sheet Income Log
A1: Date | B1: Client | C1: Invoice # | D1: Description | E1: Amount | F1: Date Paid

Sheet Expense Log
A1: Date | B1: Category | C1: Vendor | D1: Amount | E1: Deductible % | F1: Deductible Amount | G1: Notes
E2: =IF(B2="Meals",50,IF(B2="","",100)) | F2: =IF(OR(D2="",B2=""),"",D2*(E2/100))
E3: =IF(B3="Meals",50,IF(B3="","",100)) | F3: =IF(OR(D3="",B3=""),"",D3*(E3/100))
E4: =IF(B4="Meals",50,IF(B4="","",100)) | F4: =IF(OR(D4="",B4=""),"",D4*(E4/100))
E5: =IF(B5="Meals",50,IF(B5="","",100)) | F5: =IF(OR(D5="",B5=""),"",D5*(E5/100))
E6: =IF(B6="Meals",50,IF(B6="","",100)) | F6: =IF(OR(D6="",B6=""),"",D6*(E6/100))
E7: =IF(B7="Meals",50,IF(B7="","",100)) | F7: =IF(OR(D7="",B7=""),"",D7*(E7/100))
E8: =IF(B8="Meals",50,IF(B8="","",100)) | F8: =IF(OR(D8="",B8=""),"",D8*(E8/100))
E9: =IF(B9="Meals",50,IF(B9="","",100)) | F9: =IF(OR(D9="",B9=""),"",D9*(E9/100))
E10: =IF(B10="Meals",50,IF(B10="","",100)) | F10: =IF(OR(D10="",B10=""),"",D10*(E10/100))
E11: =IF(B11="Meals",50,IF(B11="","",100)) | F11: =IF(OR(D11="",B11=""),"",D11*(E11/100))
E12: =IF(B12="Meals",50,IF(B12="","",100)) | F12: =IF(OR(D12="",B12=""),"",D12*(E12/100))
E13: =IF(B13="Meals",50,IF(B13="","",100)) | F13: =IF(OR(D13="",B13=""),"",D13*(E13/100))
... E301: =IF(B301="Meals",50,IF(B301="","",100)) | F301: =IF(OR(D301="",B301=""),"",D301*(E301/100))
A303: Deductible % auto-fills to 50% for Meals, 100% otherwise — overwrite any cell if your real business-use share is different (e.g. a partly-personal vehicle or phone line).

Sheet Quarterly Tax Estimator
A2: Quarterly Tax Estimator
A4: Net profit YTD (from logs) | B4: =SUM('Income Log'!E2:E301) - SUM('Expense Log'!F2:F301) | D4: 2026 Payment Deadlines
A5: Projected full-year net profit (edit this) | B5: 60000 | D5: Quarter | E5: Due Date
D6: Q1 2026 | E6: April 15, 2026
A7: Net earnings from self-employment | B7: =B5*0.9235 | D7: Q2 2026 | E7: June 15, 2026
A8: Social Security tax (12.4%, capped at $184,500 wage base) | B8: =MIN(B7,184500)*0.124 | D8: Q3 2026 | E8: September 15, 2026
A9: Medicare tax (2.9%, no cap) | B9: =B7*0.029 | D9: Q4 2026 | E9: January 15, 2027
A10: Total self-employment tax | B10: =B8+B9
A11: Deductible half of SE tax (for income tax return) | B11: =B10/2 | D11: Days until next deadline | E11: =MIN(IF(DATE(2026,4,15)>=TODAY(),DATE(2026,4,15)-TODAY(),9999),IF(DATE(2026,6,15)>=TODAY(),DATE(2026,6,15)-TODAY(),9999),IF(DATE(2026,9,15)>=TODAY(),DATE(2026,9,15)-TODAY(),9999),IF(DATE(2027,1,15)>=TODAY(),DATE(2027,1,15)-TODAY(),9999))
A13: Suggested total tax reserve (25%-30% rule of thumb)
A14: Low estimate (25% of projected net profit) | B14: =B5*0.25
A15: High estimate (30% of projected net profit) | B15: =B5*0.30
A17: Suggested payment THIS quarter (reserve ÷ 4) | B17: =B14/4
A18: to | B18: =B15/4
A20: This tab calculates self-employment tax exactly (it's fixed math). The 25%-30% total reserve is a rule-of-thumb range that also covers income tax — your real income-tax rate depends on filing status, deductions, and state. Use the IRS Form 1040-ES worksheet or a tax preparer for a personalized income-tax figure.

Sheet Dashboard
A2: Dashboard
D3: Category | E3: Amount
A4: Total income YTD | B4: =SUM('Income Log'!E2:E301) | D4: Advertising | E4: =SUMIF('Expense Log'!$B$2:$B$301,D4,'Expense Log'!$F$2:$F$301)
A5: Total deductible expenses YTD | B5: =SUM('Expense Log'!F2:F301) | D5: Car and Truck Expenses | E5: =SUMIF('Expense Log'!$B$2:$B$301,D5,'Expense Log'!$F$2:$F$301)
A6: Net profit YTD | B6: =B4-B5 | D6: Commissions and Fees | E6: =SUMIF('Expense Log'!$B$2:$B$301,D6,'Expense Log'!$F$2:$F$301)
D7: Contract Labor | E7: =SUMIF('Expense Log'!$B$2:$B$301,D7,'Expense Log'!$F$2:$F$301)
A8: Suggested quarterly payment (from Estimator tab) | B8: ='Quarterly Tax Estimator'!B17 | D8: Depreciation & Section 179 | E8: =SUMIF('Expense Log'!$B$2:$B$301,D8,'Expense Log'!$F$2:$F$301)
A9: Days until next deadline | B9: ='Quarterly Tax Estimator'!E11 | D9: Insurance (other than health) | E9: =SUMIF('Expense Log'!$B$2:$B$301,D9,'Expense Log'!$F$2:$F$301)
D10: Legal & Professional Services | E10: =SUMIF('Expense Log'!$B$2:$B$301,D10,'Expense Log'!$F$2:$F$301)
D11: Office Expense | E11: =SUMIF('Expense Log'!$B$2:$B$301,D11,'Expense Log'!$F$2:$F$301)
D12: Rent — Other Business Property | E12: =SUMIF('Expense Log'!$B$2:$B$301,D12,'Expense Log'!$F$2:$F$301)
D13: Repairs & Maintenance | E13: =SUMIF('Expense Log'!$B$2:$B$301,D13,'Expense Log'!$F$2:$F$301)
D14: Supplies | E14: =SUMIF('Expense Log'!$B$2:$B$301,D14,'Expense Log'!$F$2:$F$301)
D15: Taxes & Licenses | E15: =SUMIF('Expense Log'!$B$2:$B$301,D15,'Expense Log'!$F$2:$F$301)
D16: Travel | E16: =SUMIF('Expense Log'!$B$2:$B$301,D16,'Expense Log'!$F$2:$F$301)
D17: Meals | E17: =SUMIF('Expense Log'!$B$2:$B$301,D17,'Expense Log'!$F$2:$F$301)
D18: Utilities | E18: =SUMIF('Expense Log'!$B$2:$B$301,D18,'Expense Log'!$F$2:$F$301)
D19: Other Expenses | E19: =SUMIF('Expense Log'!$B$2:$B$301,D19,'Expense Log'!$F$2:$F$301)
D20: Home Office | E20: =SUMIF('Expense Log'!$B$2:$B$301,D20,'Expense Log'!$F$2:$F$301)
D21: Other | E21: =SUMIF('Expense Log'!$B$2:$B$301,D21,'Expense Log'!$F$2:$F$301)
A24: Update your logs weekly — this dashboard is only as current as your last entry.
